<?xml version="1.0" encoding="UTF-8"?>
<!DOCTYPE mapper PUBLIC "-//mybatis.org//DTD Mapper 3.0//EN" "http://mybatis.org/dtd/mybatis-3-mapper.dtd">
<mapper namespace="net.suncaper.demo.mapper.ResignMapper">
    <resultMap id="ResignResultMap" type="net.suncaper.demo.common.domain.Resign">
        <!--
          WARNING - @mbg.generated
          This element is automatically generated by MyBatis Generator, do not modify.
          This element was generated on Mon Mar 01 16:16:43 GMT+08:00 2021.
        -->
            <result column="Id"  jdbcType="INTEGER" property="id"/>
            <result column="company_id"  jdbcType="INTEGER" property="companyId"/>
            <result column="worker_id"  jdbcType="INTEGER" property="workerId"/>
            <result column="content"  jdbcType="VARCHAR" property="content"/>
            <result column="isConsent"  jdbcType="VARCHAR" property="isconsent"/>
            <result column="name"  jdbcType="VARCHAR" property="companyName"/>
    </resultMap>
    <select id="getResignListByWorkerid" resultMap="ResignResultMap" parameterType="INTEGER">
        select resign.Id,company.name,resign.content,resign.isConsent
        from company, resign where company.Id = resign.Company_id AND resign.Worker_id = #{workerId}
        order by case when resign.isConsent='0' then 0 else 1 end
    </select>
</mapper>