<?xml version="1.0" encoding="UTF-8"?>
<!DOCTYPE mapper PUBLIC "-//mybatis.org//DTD Mapper 3.0//EN" "http://mybatis.org/dtd/mybatis-3-mapper.dtd">
<mapper namespace="net.suncaper.demo.mapper.ApplyMapper">
  <resultMap id="BaseResultMap" type="net.suncaper.demo.common.domain.Apply">
    <!--
      WARNING - @mbg.generated
      This element is automatically generated by MyBatis Generator, do not modify.
      This element was generated on Mon Mar 01 19:52:06 GMT+08:00 2021.
    -->
    <constructor>
      <idArg column="Id" javaType="java.lang.Integer" jdbcType="INTEGER" />
      <arg column="workerid" javaType="java.lang.Integer" jdbcType="INTEGER" />
      <arg column="companyid" javaType="java.lang.Integer" jdbcType="INTEGER" />
      <arg column="isConsent" javaType="java.lang.Integer" jdbcType="INTEGER" />
    </constructor>
  </resultMap>
  <sql id="Example_Where_Clause">
    <!--
      WARNING - @mbg.generated
      This element is automatically generated by MyBatis Generator, do not modify.
      This element was generated on Mon Mar 01 19:52:06 GMT+08:00 2021.
    -->
    <where>
      <foreach collection="oredCriteria" item="criteria" separator="or">
        <if test="criteria.valid">
          <trim prefix="(" prefixOverrides="and" suffix=")">
            <foreach collection="criteria.criteria" item="criterion">
              <choose>
                <when test="criterion.noValue">
                  and ${criterion.condition}
                </when>
                <when test="criterion.singleValue">
                  and ${criterion.condition} #{criterion.value}
                </when>
                <when test="criterion.betweenValue">
                  and ${criterion.condition} #{criterion.value} and #{criterion.secondValue}
                </when>
                <when test="criterion.listValue">
                  and ${criterion.condition}
                  <foreach close=")" collection="criterion.value" item="listItem" open="(" separator=",">
                    #{listItem}
                  </foreach>
                </when>
              </choose>
            </foreach>
          </trim>
        </if>
      </foreach>
    </where>
  </sql>
  <sql id="Update_By_Example_Where_Clause">
    <!--
      WARNING - @mbg.generated
      This element is automatically generated by MyBatis Generator, do not modify.
      This element was generated on Mon Mar 01 19:52:06 GMT+08:00 2021.
    -->
    <where>
      <foreach collection="example.oredCriteria" item="criteria" separator="or">
        <if test="criteria.valid">
          <trim prefix="(" prefixOverrides="and" suffix=")">
            <foreach collection="criteria.criteria" item="criterion">
              <choose>
                <when test="criterion.noValue">
                  and ${criterion.condition}
                </when>
                <when test="criterion.singleValue">
                  and ${criterion.condition} #{criterion.value}
                </when>
                <when test="criterion.betweenValue">
                  and ${criterion.condition} #{criterion.value} and #{criterion.secondValue}
                </when>
                <when test="criterion.listValue">
                  and ${criterion.condition}
                  <foreach close=")" collection="criterion.value" item="listItem" open="(" separator=",">
                    #{listItem}
                  </foreach>
                </when>
              </choose>
            </foreach>
          </trim>
        </if>
      </foreach>
    </where>
  </sql>
  <sql id="Base_Column_List">
    <!--
      WARNING - @mbg.generated
      This element is automatically generated by MyBatis Generator, do not modify.
      This element was generated on Mon Mar 01 19:52:06 GMT+08:00 2021.
    -->
    Id, workerid, companyid, isConsent
  </sql>
  <select id="selectByExample" parameterType="net.suncaper.demo.common.domain.ApplyExample" resultMap="BaseResultMap">
    <!--
      WARNING - @mbg.generated
      This element is automatically generated by MyBatis Generator, do not modify.
      This element was generated on Mon Mar 01 19:52:06 GMT+08:00 2021.
    -->
    select
    <if test="distinct">
      distinct
    </if>
    <include refid="Base_Column_List" />
    from apply
    <if test="_parameter != null">
      <include refid="Example_Where_Clause" />
    </if>
    <if test="orderByClause != null">
      order by ${orderByClause}
    </if>
  </select>
  <select id="selectByPrimaryKey" parameterType="java.lang.Integer" resultMap="BaseResultMap">
    <!--
      WARNING - @mbg.generated
      This element is automatically generated by MyBatis Generator, do not modify.
      This element was generated on Mon Mar 01 19:52:06 GMT+08:00 2021.
    -->
    select 
    <include refid="Base_Column_List" />
    from apply
    where Id = #{id,jdbcType=INTEGER}
  </select>
  <delete id="deleteByPrimaryKey" parameterType="java.lang.Integer">
    <!--
      WARNING - @mbg.generated
      This element is automatically generated by MyBatis Generator, do not modify.
      This element was generated on Mon Mar 01 19:52:06 GMT+08:00 2021.
    -->
    delete from apply
    where Id = #{id,jdbcType=INTEGER}
  </delete>
  <delete id="deleteByExample" parameterType="net.suncaper.demo.common.domain.ApplyExample">
    <!--
      WARNING - @mbg.generated
      This element is automatically generated by MyBatis Generator, do not modify.
      This element was generated on Mon Mar 01 19:52:06 GMT+08:00 2021.
    -->
    delete from apply
    <if test="_parameter != null">
      <include refid="Example_Where_Clause" />
    </if>
  </delete>
  <insert id="insert" parameterType="net.suncaper.demo.common.domain.Apply">
    <!--
      WARNING - @mbg.generated
      This element is automatically generated by MyBatis Generator, do not modify.
      This element was generated on Mon Mar 01 19:52:06 GMT+08:00 2021.
    -->
    insert into apply (Id, workerid, companyid, 
      isConsent)
    values (#{id,jdbcType=INTEGER}, #{workerid,jdbcType=INTEGER}, #{companyid,jdbcType=INTEGER}, 
      #{isconsent,jdbcType=INTEGER})
  </insert>
  <insert id="insertSelective" parameterType="net.suncaper.demo.common.domain.Apply">
    <!--
      WARNING - @mbg.generated
      This element is automatically generated by MyBatis Generator, do not modify.
      This element was generated on Mon Mar 01 19:52:06 GMT+08:00 2021.
    -->
    insert into apply
    <trim prefix="(" suffix=")" suffixOverrides=",">
      <if test="id != null">
        Id,
      </if>
      <if test="workerid != null">
        workerid,
      </if>
      <if test="companyid != null">
        companyid,
      </if>
      <if test="isconsent != null">
        isConsent,
      </if>
    </trim>
    <trim prefix="values (" suffix=")" suffixOverrides=",">
      <if test="id != null">
        #{id,jdbcType=INTEGER},
      </if>
      <if test="workerid != null">
        #{workerid,jdbcType=INTEGER},
      </if>
      <if test="companyid != null">
        #{companyid,jdbcType=INTEGER},
      </if>
      <if test="isconsent != null">
        #{isconsent,jdbcType=INTEGER},
      </if>
    </trim>
  </insert>
  <select id="countByExample" parameterType="net.suncaper.demo.common.domain.ApplyExample" resultType="java.lang.Long">
    <!--
      WARNING - @mbg.generated
      This element is automatically generated by MyBatis Generator, do not modify.
      This element was generated on Mon Mar 01 19:52:06 GMT+08:00 2021.
    -->
    select count(*) from apply
    <if test="_parameter != null">
      <include refid="Example_Where_Clause" />
    </if>
  </select>
  <update id="updateByExampleSelective" parameterType="map">
    <!--
      WARNING - @mbg.generated
      This element is automatically generated by MyBatis Generator, do not modify.
      This element was generated on Mon Mar 01 19:52:06 GMT+08:00 2021.
    -->
    update apply
    <set>
      <if test="record.id != null">
        Id = #{record.id,jdbcType=INTEGER},
      </if>
      <if test="record.workerid != null">
        workerid = #{record.workerid,jdbcType=INTEGER},
      </if>
      <if test="record.companyid != null">
        companyid = #{record.companyid,jdbcType=INTEGER},
      </if>
      <if test="record.isconsent != null">
        isConsent = #{record.isconsent,jdbcType=INTEGER},
      </if>
    </set>
    <if test="_parameter != null">
      <include refid="Update_By_Example_Where_Clause" />
    </if>
  </update>
  <update id="updateByExample" parameterType="map">
    <!--
      WARNING - @mbg.generated
      This element is automatically generated by MyBatis Generator, do not modify.
      This element was generated on Mon Mar 01 19:52:06 GMT+08:00 2021.
    -->
    update apply
    set Id = #{record.id,jdbcType=INTEGER},
      workerid = #{record.workerid,jdbcType=INTEGER},
      companyid = #{record.companyid,jdbcType=INTEGER},
      isConsent = #{record.isconsent,jdbcType=INTEGER}
    <if test="_parameter != null">
      <include refid="Update_By_Example_Where_Clause" />
    </if>
  </update>
  <update id="updateByPrimaryKeySelective" parameterType="net.suncaper.demo.common.domain.Apply">
    <!--
      WARNING - @mbg.generated
      This element is automatically generated by MyBatis Generator, do not modify.
      This element was generated on Mon Mar 01 19:52:06 GMT+08:00 2021.
    -->
    update apply
    <set>
      <if test="workerid != null">
        workerid = #{workerid,jdbcType=INTEGER},
      </if>
      <if test="companyid != null">
        companyid = #{companyid,jdbcType=INTEGER},
      </if>
      <if test="isconsent != null">
        isConsent = #{isconsent,jdbcType=INTEGER},
      </if>
    </set>
    where Id = #{id,jdbcType=INTEGER}
  </update>
  <update id="updateByPrimaryKey" parameterType="net.suncaper.demo.common.domain.Apply">
    <!--
      WARNING - @mbg.generated
      This element is automatically generated by MyBatis Generator, do not modify.
      This element was generated on Mon Mar 01 19:52:06 GMT+08:00 2021.
    -->
    update apply
    set workerid = #{workerid,jdbcType=INTEGER},
      companyid = #{companyid,jdbcType=INTEGER},
      isConsent = #{isconsent,jdbcType=INTEGER}
    where Id = #{id,jdbcType=INTEGER}
  </update>
</mapper>